FlowDesign/__init__.py
FlowDesign/chatbot/Ollama.py
FlowDesign/chatbot/OpenStyle.py
FlowDesign/chatbot/VLLM.py
FlowDesign/chatbot/__init__.py
FlowDesign/chatbot/base.py
FlowDesign/chatbot/template.py
FlowDesign/flow/__init__.py
FlowDesign/flow/agent.py
FlowDesign/flow/pal.py
FlowDesign/flow/supports.py
FlowDesign/litellm/__init__.py
FlowDesign/litellm/litellm.py
FlowDesign/processor/__init__.py
FlowDesign/processor/base.py
FlowDesign/processor/machine.py
FlowDesign/processor/memory.py
FlowDesign/processor/online.py
FlowDesign/processor/parser.py
FlowDesign/processor/select.py
FlowDesign/tools/__init__.py
FlowDesign/tools/base.py
FlowDesign/utils/__init__.py
FlowDesign/utils/cache.py
FlowDesign/utils/format.py
FlowDesign/utils/pattern.py
flowdesign-0.1.0.dist-info/METADATA
flowdesign-0.1.0.dist-info/WHEEL
flowdesign-0.1.0.dist-info/top_level.txt
flowdesign-0.1.0.dist-info/RECORD
